lxml2pandas/README.MD
lxml2pandas/__init__.py
lxml2pandas/requirements.txt
lxml2pandas/thirdparty.json
lxml2pandas-0.16.dist-info/LICENSE.rst
lxml2pandas-0.16.dist-info/METADATA
lxml2pandas-0.16.dist-info/WHEEL
lxml2pandas-0.16.dist-info/top_level.txt
lxml2pandas-0.16.dist-info/RECORD
