Metadata-Version: 2.1
Name: lxml2pandas
Version: 0.16
Summary: lxml to pandas for fast web scraping
Home-page: https://github.com/hansalemaos/lxml2pandas
Author: Johannes Fischer
Author-email: aulasparticularesdealemaosp@gmail.com
License: MIT
Keywords: lxml,pandas,web scraping
Classifier: Development Status :: 4 - Beta
Classifier: Programming Language :: Python :: 3 :: Only
Classifier: Programming Language :: Python :: 3.10
Classifier: Topic :: Software Development :: Libraries :: Python Modules
Classifier: Topic :: Utilities
License-File: LICENSE.rst
Requires-Dist: a_pandas_ex_apply_ignore_exceptions
Requires-Dist: fake_headers
Requires-Dist: flatten_everything
Requires-Dist: lxml
Requires-Dist: multiprocnomain
Requires-Dist: numpy
Requires-Dist: pandas
Requires-Dist: requests
